file_encrypter_decrypter/__init__.py
file_encrypter_decrypter/led.py
file_encrypter_decrypter-0.0.3.dist-info/METADATA
file_encrypter_decrypter-0.0.3.dist-info/WHEEL
file_encrypter_decrypter-0.0.3.dist-info/top_level.txt
file_encrypter_decrypter-0.0.3.dist-info/RECORD
